LICENSE
MANIFEST.in
README.md
setup.py
cbpi/__init__.py
cbpi/cli.py
cbpi/configFolder.py
cbpi/craftbeerpi.py
cbpi/eventbus.py
cbpi/satellite.py
cbpi/websocket.py
cbpi4.egg-info/PKG-INFO
cbpi4.egg-info/SOURCES.txt
cbpi4.egg-info/dependency_links.txt
cbpi4.egg-info/entry_points.txt
cbpi4.egg-info/requires.txt
cbpi4.egg-info/top_level.txt
cbpi/api/__init__.py
cbpi/api/actor.py
cbpi/api/base.py
cbpi/api/config.py
cbpi/api/dataclasses.py
cbpi/api/decorator.py
cbpi/api/exceptions.py
cbpi/api/extension.py
cbpi/api/fermenter_logic.py
cbpi/api/kettle_logic.py
cbpi/api/property.py
cbpi/api/sensor.py
cbpi/api/step.py
cbpi/api/timer.py
cbpi/config/actor.json
cbpi/config/chromium.desktop
cbpi/config/config.json
cbpi/config/config.yaml
cbpi/config/craftbeerpi.template
cbpi/config/craftbeerpiboot
cbpi/config/create_database.sql
cbpi/config/fermenter_data.json
cbpi/config/kettle.json
cbpi/config/plugin_list.txt
cbpi/config/sensor.json
cbpi/config/splash.png
cbpi/config/step_data.json
cbpi/controller/__init__.py
cbpi/controller/actor_controller.py
cbpi/controller/basic_controller2.py
cbpi/controller/config_controller.py
cbpi/controller/dashboard_controller.py
cbpi/controller/fermentation_controller.py
cbpi/controller/fermenter_recipe_controller.py
cbpi/controller/job_controller.py
cbpi/controller/kettle_controller.py
cbpi/controller/log_file_controller.py
cbpi/controller/notification_controller.py
cbpi/controller/plugin_controller.py
cbpi/controller/recipe_controller.py
cbpi/controller/satellite_controller.py
cbpi/controller/sensor_controller.py
cbpi/controller/step_controller.py
cbpi/controller/system_controller.py
cbpi/controller/upload_controller.py
cbpi/extension/__init__.py
cbpi/extension/ConfigUpdate/__init__.py
cbpi/extension/ConfigUpdate/config.yaml
cbpi/extension/ConfigUpdate/__pycache__/__init__.cpython-311.pyc
cbpi/extension/ConfigUpdate/__pycache__/__init__.cpython-312.pyc
cbpi/extension/ConfigUpdate/__pycache__/__init__.cpython-313.pyc
cbpi/extension/ConfigUpdate/__pycache__/__init__.cpython-314.pyc
cbpi/extension/FermentationStep/__init__.py
cbpi/extension/FermentationStep/config.yaml
