Metadata-Version: 2.4
Name: cbpi4
Version: 4.7.1
Summary: CraftBeerPi4 Brewing Software
Home-page: https://github.com/PiBrewing/craftbeerpi4
Author: Manuel Fritsch / Alexander Vollkopf
Author-email: avollkopf@l@web.de
License: GPLv3
Project-URL: Documentation, https://openbrewing.gitbook.io/craftbeerpi4_support/
Requires-Python: >=3.9
License-File: LICENSE
Requires-Dist: typing-extensions>=4
Requires-Dist: aiohttp==3.13.3
Requires-Dist: aiohttp-auth==0.1.1
Requires-Dist: aiohttp-route-decorator==0.1.4
Requires-Dist: aiohttp-security==0.5.0
Requires-Dist: aiohttp-session==2.12.1
Requires-Dist: aiohttp-swagger==1.0.16
Requires-Dist: aiojobs==1.4.0
Requires-Dist: aiosqlite==0.22.1
Requires-Dist: cryptography==46.0.3
Requires-Dist: pyopenssl==25.3.0
Requires-Dist: requests==2.32.5
Requires-Dist: voluptuous==0.15.2
Requires-Dist: pyfiglet==1.0.4
Requires-Dist: click==8.3.1
Requires-Dist: shortuuid==1.0.13
Requires-Dist: tabulate==0.9.0
Requires-Dist: aiomqtt==2.5.0
Requires-Dist: inquirer==3.4.1
Requires-Dist: colorama==0.4.6
Requires-Dist: psutil==7.1.3
Requires-Dist: cbpi4gui
Requires-Dist: importlib_metadata
Requires-Dist: distro>=1.8.0
Requires-Dist: numpy==2.3.5
Requires-Dist: pandas==2.3.3
Dynamic: author
Dynamic: author-email
Dynamic: description
Dynamic: description-content-type
Dynamic: home-page
Dynamic: license
Dynamic: license-file
Dynamic: project-url
Dynamic: requires-dist
Dynamic: requires-python
Dynamic: summary
